tgz_messaging/__init__.py
tgz_messaging/message_client/__init__.py
tgz_messaging/message_client/api/__init__.py
tgz_messaging/message_client/api/api_client.py
tgz_messaging/message_client/api/domain/__init__.py
tgz_messaging/message_client/api/domain/base.py
tgz_messaging/message_client/base/__init__.py
tgz_messaging/message_client/base/client.py
tgz_messaging/message_client/email/__init__.py
tgz_messaging/message_client/whatsapp/__init__.py
tgz_messaging/message_client/whatsapp/client.py
tgz_messaging/message_type/__init__.py
tgz_messaging/message_type/base/__init__.py
tgz_messaging/message_type/base/message_type.py
tgz_messaging/message_type/broadcast/__init__.py
tgz_messaging/message_type/broadcast/base/__init__.py
tgz_messaging/message_type/broadcast/base/broadcast.py
tgz_messaging/message_type/broadcast/email/__init__.py
tgz_messaging/message_type/broadcast/email/broadcast.py
tgz_messaging/message_type/broadcast/whatsapp/__init__.py
tgz_messaging/message_type/broadcast/whatsapp/broadcast.py
tgz_messaging/message_type/direct/__init__.py
tgz_messaging/message_type/direct/base/__init__.py
tgz_messaging/message_type/direct/base/direct.py
tgz_messaging/message_type/direct/email/__init__.py
tgz_messaging/message_type/direct/email/direct.py
tgz_messaging/message_type/direct/whatsapp/__init__.py
tgz_messaging/message_type/direct/whatsapp/direct.py
tgz_messaging/messaging/__init__.py
tgz_messaging/messaging/messaging.py
tgz_messaging/messaging/base/__init__.py
tgz_messaging/messaging/base/messaging.py
tgzmessaging_sdk-0.0.4.dist-info/METADATA
tgzmessaging_sdk-0.0.4.dist-info/WHEEL
tgzmessaging_sdk-0.0.4.dist-info/top_level.txt
tgzmessaging_sdk-0.0.4.dist-info/RECORD
