Metadata-Version: 2.4
Name: tgzmessaging-sdk
Version: 0.0.4
Summary: An Official Python SDK from TechGenzi for sending messages across multiple channels like WhatsApp, Email, and SMS.
Author-email: Suwethan M <suwethan.tgz@gmail.com>
License: MIT
Requires-Python: >=3.7
